[
  {
    "inputs": [
      {
        "internalType": "address",
        "name": "flip_",
        "type": "address"
      }
    ],
    "stateMutability": "nonpayable",
    "type": "constructor"
  },
  {
    "inputs": [
      {
        "internalType": "bytes32",
        "name": "nodeID",
        "type": "bytes32"
      }
    ],
    "name": "executeRedemption",
    "outputs": [
      {
        "internalType": "uint256",
        "name": "",
        "type": "uint256"
      }
    ],
    "stateMutability": "nonpayable",
    "type": "function"
  },
  {
    "inputs": [],
    "name": "flip",
    "outputs": [
      {
        "internalType": "contract IERC20",
        "name": "",
        "type": "address"
      }
    ],
    "stateMutability": "view",
    "type": "function"
  },
  {
    "inputs": [
      {
        "internalType": "bytes32",
        "name": "nodeID",
        "type": "bytes32"
      },
      {
        "internalType": "uint256",
        "name": "amount",
        "type": "uint256"
      }
    ],
    "name": "fundStateChainAccount",
    "outputs": [],
    "stateMutability": "nonpayable",
    "type": "function"
  }
]